psyneulink_fastkde-1.0.19.dist-info/WHEEL
psyneulink_fastkde-1.0.19.dist-info/LICENSE.txt
psyneulink_fastkde-1.0.19.dist-info/top_level.txt
psyneulink_fastkde-1.0.19.dist-info/RECORD
psyneulink_fastkde-1.0.19.dist-info/METADATA
fastkde/version.py
fastkde/empiricalCharacteristicFunction.py
fastkde/plot.py
fastkde/nufft.cpython-37m-aarch64-linux-gnu.so
fastkde/fastKDE.py
fastkde/__init__.py
fastkde/floodFillSearch.cpython-37m-aarch64-linux-gnu.so
