Metadata-Version: 2.1
Name: psyneulink-fastkde
Version: 1.0.19
Summary: Tools for fast and robust univariate and multivariate kernel density estimation
Home-page: https://github.com/LBL-EESA/fastkde
Author: Travis A. O'Brien
Author-email: obrienta@iu.edu
License: UNKNOWN
Download-URL: https://github.com/LBL-EESA/fastkde/archive/v1.0.17tar.gz
Keywords: statistics,probability,KDE,kernel density estimation
Platform: UNKNOWN
Requires-Dist: numpy
Requires-Dist: scipy
Requires-Dist: cython
Provides-Extra: all
Requires-Dist: pytest ; extra == 'all'
Provides-Extra: dev
Requires-Dist: pytest ; extra == 'dev'
Provides-Extra: test
Requires-Dist: pytest ; extra == 'test'
